{"is_source_file": true, "format": "JavaScript (React JSX)", "description": "This file is the main React component for a Tic Tac Toe game, implementing the UI, game logic, state management, and accessibility features.", "external_files": ["./App.css"], "external_methods": ["console.log"], "published": ["App", "Board", "Cell", "StatusBar", "Controls", "calculateWinner", "logger"], "classes": [], "methods": [{"name": "logger(...args)", "description": "Environment-aware logging function that logs based on environment variables.", "scope": "", "scopeKind": ""}, {"name": "calculateWinner(squares)", "description": "Determines if there is a winner in the current game board.", "scope": "", "scopeKind": ""}, {"name": "App()", "description": "Main React component that manages the game state, UI, and game logic for Tic Tac Toe.", "scope": "", "scopeKind": ""}, {"name": "Board({ renderCell })", "description": "Render the 3x3 grid of the Tic Tac Toe game.", "scope": "", "scopeKind": ""}, {"name": "Cell({ index, value, onSelect, disabled, isWinning, cellRef, onKeyDown, })", "description": "A single game cell, accessible and stylized, representing a square in the grid.", "scope": "", "scopeKind": ""}, {"name": "StatusBar({ status })", "description": "Displays current game status message.", "scope": "", "scopeKind": ""}, {"name": "Controls({ onReset, gameOver, resetBtnRef })", "description": "Contains the reset button for the game.", "scope": "", "scopeKind": ""}], "calls": ["console.log", "calculateWinner", "useState", "useEffect", "useRef", "useCallback", "setBoard", "setIsXNext", "setStatus", "setGameOver", "setWinnerLine", "focus"], "search-terms": ["Tic Tac Toe React component", "game logic", "keyboard navigation", "accessibility", "game reset", "winner calculation", "status bar", "game board"], "state": 2, "file_id": 6, "knowledge_revision": 26, "git_revision": "7fd3e55913ca3904cfa025cdf08c99ccdd35bc0c", "revision_history": [{"23": "7fd3e55913ca3904cfa025cdf08c99ccdd35bc0c"}, {"26": "7fd3e55913ca3904cfa025cdf08c99ccdd35bc0c"}], "ctags": [{"_type": "tag", "name": "0", "path": "/home/kavia/workspace/code-generation/two-player-tic-tac-toe-277692-277702/tic_tac_toe_frontend/src/App.js", "pattern": "/^        tabIndex={0}$/", "language": "JavaScript", "kind": "field", "scope": "tabIndex", "scopeKind": "class"}, {"_type": "tag", "name": "0", "path": "/home/kavia/workspace/code-generation/two-player-tic-tac-toe-277692-277702/tic_tac_toe_frontend/src/App.js", "pattern": "/^      tabIndex={0}$/", "language": "JavaScript", "kind": "field", "scope": "Board.tabIndex", "scopeKind": "class"}, {"_type": "tag", "name": "0", "path": "/home/kavia/workspace/code-generation/two-player-tic-tac-toe-277692-277702/tic_tac_toe_frontend/src/App.js", "pattern": "/^      tabIndex={0}$/", "language": "JavaScript", "kind": "field", "scope": "Cell.tabIndex", "scopeKind": "class"}, {"_type": "tag", "name": "3", "path": "/home/kavia/workspace/code-generation/two-player-tic-tac-toe-277692-277702/tic_tac_toe_frontend/src/App.js", "pattern": "/^      aria-colcount={3}$/", "language": "JavaScript", "kind": "field", "scope": "Board.aria", "scopeKind": "class"}, {"_type": "tag", "name": "3", "path": "/home/kavia/workspace/code-generation/two-player-tic-tac-toe-277692-277702/tic_tac_toe_frontend/src/App.js", "pattern": "/^      aria-rowcount={3}$/", "language": "JavaScript", "kind": "field", "scope": "Board.aria", "scopeKind": "class"}, {"_type": "tag", "name": "App", "path": "/home/kavia/workspace/code-generation/two-player-tic-tac-toe-277692-277702/tic_tac_toe_frontend/src/App.js", "pattern": "/^function App() {$/", "language": "JavaScript", "kind": "function", "signature": "()"}, {"_type": "tag", "name": "Board", "path": "/home/kavia/workspace/code-generation/two-player-tic-tac-toe-277692-277702/tic_tac_toe_frontend/src/App.js", "pattern": "/^function Board({ renderCell }) {$/", "language": "JavaScript", "kind": "function", "signature": "({ renderCell })"}, {"_type": "tag", "name": "COLORS", "path": "/home/kavia/workspace/code-generation/two-player-tic-tac-toe-277692-277702/tic_tac_toe_frontend/src/App.js", "pattern": "/^const COLORS = {$/", "language": "JavaScript", "kind": "class"}, {"_type": "tag", "name": "Cell", "path": "/home/kavia/workspace/code-generation/two-player-tic-tac-toe-277692-277702/tic_tac_toe_frontend/src/App.js", "pattern": "/^const Cell = React.memo(function Cell({$/", "language": "JavaScript", "kind": "constant"}, {"_type": "tag", "name": "Cell", "path": "/home/kavia/workspace/code-generation/two-player-tic-tac-toe-277692-277702/tic_tac_toe_frontend/src/App.js", "pattern": "/^const Cell = React.memo(function Cell({$/", "language": "JavaScript", "kind": "function", "signature": "({ index, value, onSelect, disabled, isWinning, cellRef, onKeyDown, })"}, {"_type": "tag", "name": "Controls", "path": "/home/kavia/workspace/code-generation/two-player-tic-tac-toe-277692-277702/tic_tac_toe_frontend/src/App.js", "pattern": "/^function Controls({ onReset, gameOver, resetBtnRef }) {$/", "language": "JavaScript", "kind": "function", "signature": "({ onReset, gameOver, resetBtnRef })"}, {"_type": "tag", "name": "StatusBar", "path": "/home/kavia/workspace/code-generation/two-player-tic-tac-toe-277692-277702/tic_tac_toe_frontend/src/App.js", "pattern": "/^function StatusBar({ status }) {$/", "language": "JavaScript", "kind": "function", "signature": "({ status })"}, {"_type": "tag", "name": "background", "path": "/home/kavia/workspace/code-generation/two-player-tic-tac-toe-277692-277702/tic_tac_toe_frontend/src/App.js", "pattern": "/^  background: \"#f9fafb\",$/", "language": "JavaScript", "kind": "property", "scope": "COLORS", "scopeKind": "class"}, {"_type": "tag", "name": "calculateWinner", "path": "/home/kavia/workspace/code-generation/two-player-tic-tac-toe-277692-277702/tic_tac_toe_frontend/src/App.js", "pattern": "/^function calculateWinner(squares) {$/", "language": "JavaScript", "kind": "function", "signature": "(squares)"}, {"_type": "tag", "name": "cellRef", "path": "/home/kavia/workspace/code-generation/two-player-tic-tac-toe-277692-277702/tic_tac_toe_frontend/src/App.js", "pattern": "/^      ref={cellRef}$/", "language": "JavaScript", "kind": "field", "scope": "Cell.ref", "scopeKind": "class"}, {"_type": "tag", "name": "disabled", "path": "/home/kavia/workspace/code-generation/two-player-tic-tac-toe-277692-277702/tic_tac_toe_frontend/src/App.js", "pattern": "/^      aria-disabled={disabled}$/", "language": "JavaScript", "kind": "field", "scope": "Cell.aria", "scopeKind": "class"}, {"_type": "tag", "name": "error", "path": "/home/kavia/workspace/code-generation/two-player-tic-tac-toe-277692-277702/tic_tac_toe_frontend/src/App.js", "pattern": "/^  error: \"#EF4444\",$/", "language": "JavaScript", "kind": "property", "scope": "COLORS", "scopeKind": "class"}, {"_type": "tag", "name": "gameOver", "path": "/home/kavia/workspace/code-generation/two-player-tic-tac-toe-277692-277702/tic_tac_toe_frontend/src/App.js", "pattern": "/^            gameOver={gameOver}$/", "language": "JavaScript", "kind": "field", "scope": "gameOver", "scopeKind": "class"}, {"_type": "tag", "name": "gradient", "path": "/home/kavia/workspace/code-generation/two-player-tic-tac-toe-277692-277702/tic_tac_toe_frontend/src/App.js", "pattern": "/^  gradient: \"linear-gradient(135deg, #2563eb1a, #f9fafb 100%)\",$/", "language": "JavaScript", "kind": "property", "scope": "COLORS", "scopeKind": "class"}, {"_type": "tag", "name": "handleReset", "path": "/home/kavia/workspace/code-generation/two-player-tic-tac-toe-277692-277702/tic_tac_toe_frontend/src/App.js", "pattern": "/^            onReset={handleReset}$/", "language": "JavaScript", "kind": "field", "scope": "onReset", "scopeKind": "class"}, {"_type": "tag", "name": "index", "path": "/home/kavia/workspace/code-generation/two-player-tic-tac-toe-277692-277702/tic_tac_toe_frontend/src/App.js", "pattern": "/^      data-index={index}$/", "language": "JavaScript", "kind": "field", "scope": "Cell.data", "scopeKind": "class"}, {"_type": "tag", "name": "initialBoard", "path": "/home/kavia/workspace/code-generation/two-player-tic-tac-toe-277692-277702/tic_tac_toe_frontend/src/App.js", "pattern": "/^const initialBoard = Array(9).fill(null);$/", "language": "JavaScript", "kind": "constant"}, {"_type": "tag", "name": "isWinning", "path": "/home/kavia/workspace/code-generation/two-player-tic-tac-toe-277692-277702/tic_tac_toe_frontend/src/App.js", "pattern": "/^      style={isWinning$/", "language": "JavaScript", "kind": "field", "scope": "Cell.style", "scopeKind": "class"}, {"_type": "tag", "name": "logger", "path": "/home/kavia/workspace/code-generation/two-player-tic-tac-toe-277692-277702/tic_tac_toe_frontend/src/App.js", "pattern": "/^function logger(...args) {$/", "language": "JavaScript", "kind": "function", "signature": "(...args)"}, {"_type": "tag", "name": "onReset", "path": "/home/kavia/workspace/code-generation/two-player-tic-tac-toe-277692-277702/tic_tac_toe_frontend/src/App.js", "pattern": "/^        onClick={onReset}$/", "language": "JavaScript", "kind": "field", "scope": "Controls.onClick", "scopeKind": "class"}, {"_type": "tag", "name": "primary", "path": "/home/kavia/workspace/code-generation/two-player-tic-tac-toe-277692-277702/tic_tac_toe_frontend/src/App.js", "pattern": "/^  primary: \"#2563EB\",$/", "language": "JavaScript", "kind": "property", "scope": "COLORS", "scopeKind": "class"}, {"_type": "tag", "name": "resetBtnRef", "path": "/home/kavia/workspace/code-generation/two-player-tic-tac-toe-277692-277702/tic_tac_toe_frontend/src/App.js", "pattern": "/^            resetBtnRef={resetBtnRef}$/", "language": "JavaScript", "kind": "field", "scope": "resetBtnRef", "scopeKind": "class"}, {"_type": "tag", "name": "resetBtnRef", "path": "/home/kavia/workspace/code-generation/two-player-tic-tac-toe-277692-277702/tic_tac_toe_frontend/src/App.js", "pattern": "/^        ref={resetBtnRef}$/", "language": "JavaScript", "kind": "field", "scope": "Controls.ref", "scopeKind": "class"}, {"_type": "tag", "name": "secondary", "path": "/home/kavia/workspace/code-generation/two-player-tic-tac-toe-277692-277702/tic_tac_toe_frontend/src/App.js", "pattern": "/^  secondary: \"#F59E0B\",$/", "language": "JavaScript", "kind": "property", "scope": "COLORS", "scopeKind": "class"}, {"_type": "tag", "name": "surface", "path": "/home/kavia/workspace/code-generation/two-player-tic-tac-toe-277692-277702/tic_tac_toe_frontend/src/App.js", "pattern": "/^  surface: \"#ffffff\",$/", "language": "JavaScript", "kind": "property", "scope": "COLORS", "scopeKind": "class"}, {"_type": "tag", "name": "text", "path": "/home/kavia/workspace/code-generation/two-player-tic-tac-toe-277692-277702/tic_tac_toe_frontend/src/App.js", "pattern": "/^  text: \"#111827\",$/", "language": "JavaScript", "kind": "property", "scope": "COLORS", "scopeKind": "class"}, {"_type": "tag", "name": "ttt-cell${isWinning ? \" ttt-cell-win\" : \"\"}", "path": "/home/kavia/workspace/code-generation/two-player-tic-tac-toe-277692-277702/tic_tac_toe_frontend/src/App.js", "pattern": "/^      className={`ttt-cell${isWinning ? \" ttt-cell-win\" : \"\"}`}$/", "language": "JavaScript", "kind": "field", "scope": "Cell.className", "scopeKind": "class"}, {"_type": "tag", "name": "value", "path": "/home/kavia/workspace/code-generation/two-player-tic-tac-toe-277692-277702/tic_tac_toe_frontend/src/App.js", "pattern": "/^      aria-label={value ? `Cell ${index + 1}, ${value}` : `Cell ${index + 1}, empty`}$/", "language": "JavaScript", "kind": "field", "scope": "Cell.aria", "scopeKind": "class"}], "hash": "e97cece47df2abe3611da099c25f0c20", "format-version": 4, "code-base-name": "tic_tac_toe_frontend", "filename": "tic_tac_toe_frontend/src/App.js", "fields": [{"name": "tabIndex={0}", "scope": "tabIndex", "scopeKind": "class", "description": "unavailable"}, {"name": "aria-colcount={3}", "scope": "Board.aria", "scopeKind": "class", "description": "unavailable"}, {"name": "aria-rowcount={3}", "scope": "Board.aria", "scopeKind": "class", "description": "unavailable"}, {"name": "background: \"#f9fafb\",", "scope": "COLORS", "scopeKind": "class", "description": "unavailable"}, {"name": "ref={cellRef}", "scope": "Cell.ref", "scopeKind": "class", "description": "unavailable"}, {"name": "aria-disabled={disabled}", "scope": "Cell.aria", "scopeKind": "class", "description": "unavailable"}, {"name": "error: \"#EF4444\",", "scope": "COLORS", "scopeKind": "class", "description": "unavailable"}, {"name": "gameOver={gameOver}", "scope": "gameOver", "scopeKind": "class", "description": "unavailable"}, {"name": "gradient: \"linear-gradient(135deg, #2563eb1a, #f9fafb 100%)\",", "scope": "COLORS", "scopeKind": "class", "description": "unavailable"}, {"name": "onReset={handleReset}", "scope": "onReset", "scopeKind": "class", "description": "unavailable"}, {"name": "data-index={index}", "scope": "Cell.data", "scopeKind": "class", "description": "unavailable"}, {"name": "style={isWinning", "scope": "Cell.style", "scopeKind": "class", "description": "unavailable"}, {"name": "onClick={onReset}", "scope": "Controls.onClick", "scopeKind": "class", "description": "unavailable"}, {"name": "primary: \"#2563EB\",", "scope": "COLORS", "scopeKind": "class", "description": "unavailable"}, {"name": "resetBtnRef={resetBtnRef}", "scope": "resetBtnRef", "scopeKind": "class", "description": "unavailable"}, {"name": "ref={resetBtnRef}", "scope": "Controls.ref", "scopeKind": "class", "description": "unavailable"}, {"name": "secondary: \"#F59E0B\",", "scope": "COLORS", "scopeKind": "class", "description": "unavailable"}, {"name": "surface: \"#ffffff\",", "scope": "COLORS", "scopeKind": "class", "description": "unavailable"}, {"name": "text: \"#111827\",", "scope": "COLORS", "scopeKind": "class", "description": "unavailable"}, {"name": "className={`ttt-cell${isWinning ? \" ttt-cell-win\" : \"\"}`}", "scope": "Cell.className", "scopeKind": "class", "description": "unavailable"}, {"name": "aria-label={value ? `Cell ${index + 1}, ${value}` : `Cell ${index + 1}, empty`}", "scope": "Cell.aria", "scopeKind": "class", "description": "unavailable"}]}